kolada/__init__.py
kolada-0.0.0.dist-info/METADATA
kolada-0.0.0.dist-info/WHEEL
kolada-0.0.0.dist-info/top_level.txt
kolada-0.0.0.dist-info/RECORD
